retargeting/__init__.py
retargeting/_version.py
retargeting/filters.py
retargeting/hand.py
retargeting/py.typed
retargeting/robot.py
retargeting/robot_wrapper.py
retargeting/typing.py
retargeting/utils.py
retargeting/visualizer.py
retargeting/conf/gr1t1.yaml
retargeting/conf/gr2t2d.yaml
retargeting/configs/__init__.py
retargeting/configs/common.py
retargeting/configs/filter.py
retargeting/configs/hand.py
retargeting/configs/ik.py
retargeting/configs/robot.py
retargeting/stubs/pinocchio.pyi
retargeting-0.1.0.dist-info/METADATA
retargeting-0.1.0.dist-info/WHEEL
retargeting-0.1.0.dist-info/RECORD
