Metadata-Version: 2.4
Name: retargeting
Version: 0.1.0
Summary: Add your description here
Requires-Python: >=3.10
Requires-Dist: beartype>=0.21.0
Requires-Dist: daqp>=0.7.1
Requires-Dist: dex-retargeting>=0.5.0
Requires-Dist: fourier-robot-descriptions[yourdfpy]==0.2.5.dev3
Requires-Dist: ischedule>=1.2.7
Requires-Dist: jaxtyping>=0.3.2
Requires-Dist: loguru>=0.7.3
Requires-Dist: numba>=0.61.2
Requires-Dist: numpy>=2.2.6
Requires-Dist: omegaconf>=2.3.0
Requires-Dist: pin-pink>=3.3.0
Provides-Extra: viz
Requires-Dist: meshcat>=0.3.2; extra == 'viz'
Requires-Dist: uvloop>=0.21.0; extra == 'viz'
Requires-Dist: viser>=0.2.23; extra == 'viz'
